farmquest/FarmQuest.py
farmquest/__init__.py
farmquest-0.0.5.dist-info/METADATA
farmquest-0.0.5.dist-info/WHEEL
farmquest-0.0.5.dist-info/top_level.txt
farmquest-0.0.5.dist-info/RECORD
