Metadata-Version: 2.1
Name: farmquest
Version: 0.0.5
Summary: Python package to interact with the FarmQuest WebService
Home-page: https://github.com/agri-marche/farmquest
Author: Régis Tremblay Lefrançois
Author-email: rtlefrancois@agri-marche.com
Project-URL: Bug Tracker, https://github.com/agri-marche/farmquest/issues
Classifier: Programming Language :: Python :: 3
Classifier: License :: OSI Approved :: MIT License
Classifier: Operating System :: OS Independent
Requires-Python: >=3.8
Requires-Dist: requests
